upoints/gpx.py
upoints/point.py
upoints/nmea.py
upoints/tzdata.py
upoints/geonames.py
upoints/compat.py
upoints/cellid.py
upoints/_version.py
upoints/utils.py
upoints/xearth.py
upoints/cities.py
upoints/__init__.py
upoints/weather_stations.py
upoints/osm.py
upoints/edist.py
upoints/baken.py
upoints/trigpoints.py
upoints/kml.py
upoints-0.12.2.data/scripts/edist
upoints-0.12.2.dist-info/pydist.json
upoints-0.12.2.dist-info/entry_points.txt
upoints-0.12.2.dist-info/WHEEL
upoints-0.12.2.dist-info/METADATA
upoints-0.12.2.dist-info/RECORD
upoints-0.12.2.dist-info/DESCRIPTION.rst
upoints-0.12.2.dist-info/top_level.txt
